incremname/__init__.py
incremname/incname.py
incremname-1.0.2.dist-info/METADATA
incremname-1.0.2.dist-info/WHEEL
incremname-1.0.2.dist-info/licenses/LICENSE
incremname-1.0.2.dist-info/RECORD
