Metadata-Version: 2.1
Name: incremname
Version: 1.0.2
Summary: Increments a file/folder name if it already exists
Project-URL: Homepage, https://github.com/crazytexer/incremname
Project-URL: Bug Tracker, https://github.com/crazytexer/incremname/issues
Author-email: Evgenii Shirokov <crazytexer@gmail.com>
License-File: LICENSE
Classifier: License :: OSI Approved :: MIT License
Classifier: Operating System :: OS Independent
Classifier: Programming Language :: Python :: 3
Requires-Python: >=3.8
